bloc_client/__init__.py
bloc_client/bloc_client.py
bloc_client/consumer.py
bloc_client/formcontrol_type.py
bloc_client/function.py
bloc_client/function_interface.py
bloc_client/function_ipt.py
bloc_client/function_opt.py
bloc_client/function_run_log.py
bloc_client/function_run_opt.py
bloc_client/function_run_progress_report.py
bloc_client/function_run_queue.py
bloc_client/function_run_record.py
bloc_client/function_to_run_mq_msg.py
bloc_client/internal/gen_uuid.py
bloc_client/internal/http_util.py
bloc_client/internal/rabbitmq.py
bloc_client/object_storage.py
bloc_client/select_options.py
bloc_client/value_type.py
bloc_client-0.2.7.dist-info/LICENSE
bloc_client-0.2.7.dist-info/WHEEL
bloc_client-0.2.7.dist-info/METADATA
bloc_client-0.2.7.dist-info/RECORD
