Metadata-Version: 2.1
Name: bloc-client
Version: 0.2.7
Summary: python client sdk for bloc
Author: pillipanda
Author-email: pillipanda@126.com
Requires-Python: >=3.8,<4.0
Classifier: Programming Language :: Python :: 3
Classifier: Programming Language :: Python :: 3.10
Classifier: Programming Language :: Python :: 3.8
Classifier: Programming Language :: Python :: 3.9
Requires-Dist: httpx (>=0.21.1,<0.22.0)
Requires-Dist: pika (>=1.2.0,<2.0.0)
